mothman/__init__.py
mothman/__main__.py
mothman/__version__.py
mothman/cli.py
mothman/depictions.py
mothman/pydpkg.py
mothman/repo.py
mothman/tree.py
mothman/utils.py
mothman-0.1.0.dist-info/entry_points.txt
mothman-0.1.0.dist-info/LICENSE.txt
mothman-0.1.0.dist-info/WHEEL
mothman-0.1.0.dist-info/METADATA
mothman-0.1.0.dist-info/RECORD
