Metadata-Version: 2.1
Name: mothman
Version: 0.1.0
Summary: Cydia/Sileo repo configurator/generator
Home-page: https://github.com/ongyx/mothman
Author: Ong Yong Xin
Author-email: ongyongxin2020+github@gmail.com
Requires-Python: >=3.6
Classifier: Programming Language :: Python :: 3
Classifier: License :: OSI Approved :: Apache Software License
Classifier: Operating System :: OS Independent
Requires-Dist: arpy>=1.1.1
Requires-Dist: click>=7.1.2
Requires-Dist: coloredlogs>=14.0
Requires-Dist: requests>=2.24.0
Requires-Dist: six<2.0.0
Requires-Dist: PGPy>=0.4.1 ; extra == "dsc"
Provides-Extra: dsc
